<?xml version="1.0" encoding="UTF-8"?>
<recompensas>
    <pirata>
        <id>	1	</id>
        <nome>	Mariana Froes	</nome>
        <recompensa>	Eu	</recompensa>
        <alcunha>		</alcunha>
        <sobre>  A Melancolia de Ser 'Eu': Uma Análise da Canção de Mariana Froes
A canção 'Eu', interpretada por Mariana Froes, é um mergulho introspectivo na alma da artista, onde ela expressa um desejo de escapar de si mesma e das complexidades de sua própria existência. Através de uma letra carregada de emoção, Froes busca refúgio na alma de outra pessoa ou na música, elementos que funcionam como válvulas de escape para suas inquietações internas.

A repetição do verso 'Preciso fugir de mim' sugere uma luta interna, onde a cantora se sente sobrecarregada por seus pensamentos e sentimentos. A música se torna um meio de comunicação e compreensão, uma forma de conectar-se com o outro e, ao mesmo tempo, distanciar-se de si. A expressão 'obra inacabada' revela uma percepção de si mesma como um ser em constante construção, imperfeito e em busca de completude. A 'vã melancolia' mencionada na letra pode ser interpretada como uma aceitação da tristeza e da impermanência que acompanham a jornada de autoconhecimento e a existência humana.

As metáforas 'aeronave sem asas' e 'plateia indo embora' ilustram a sensação de estar prestes a iniciar algo novo, mas ao mesmo tempo, sentir-se sozinha e sem apoio. A música de Mariana Froes é um convite para refletir sobre a complexidade do ser, a busca por significado e a aceitação das próprias emoções, mesmo aquelas que nos levam a querer fugir de quem somos.  	</sobre>
        <status>		</status>
    </pirata>
    <pirata>
        <id>	2	</id>
        <nome>	Mãeana	</nome>
        <recompensa>	Meu Pedaço De Pecado	</recompensa>
        <alcunha>		</alcunha>
        <sobre>	Paixão Ardente em 'Meu Pedaço de Pecado'
A música 'Meu Pedaço de Pecado', interpretada por Mãeana com participação de João Gomes, é uma expressão vibrante de desejo e paixão. A letra descreve intensamente o sentimento de um indivíduo que está profundamente atraído por alguém, referindo-se a essa pessoa como seu 'pedaço de pecado', uma metáfora que sugere tanto a irresistibilidade quanto a possível culpa associada ao desejo intenso.

O refrão da música, que fala sobre querer beijar novamente e sentir o corpo do outro, ressalta a forte conexão física e emocional entre os dois. A repetição dessas linhas ao longo da música amplifica a sensação de um desejo que não apenas persiste, mas cresce com o tempo. A música utiliza uma linguagem simples mas eficaz para transmitir a urgência e a profundidade desse sentimento, fazendo com que o ouvinte possa facilmente se identificar ou ser envolvido pela história.

Além disso, a colaboração entre Mãeana e João Gomes adiciona uma camada extra de autenticidade e emoção à interpretação. João Gomes, conhecido por sua voz marcante no cenário do forró e piseiro, complementa a suavidade de Mãeana, criando um dueto harmonioso que captura perfeitamente a essência da paixão descrita na letra.	</sobre>
    </pirata>
    <pirata>
        <id>	3	</id>
        <nome>	Gregory Alan Isakov	</nome>
        <recompensa>	Big Black Car	</recompensa>
        <alcunha>		</alcunha>
        <sobre>	A Nostalgia e a Melancolia em 'Big Black Car'
A música 'Big Black Car', do cantor e compositor Gregory Alan Isakov, é uma composição melancólica que reflete sobre a passagem do tempo, a perda e a memória. Através de uma narrativa poética, Isakov utiliza metáforas para descrever sentimentos de saudade e reflexões sobre o passado.

A letra começa com uma imagem nostálgica, onde o narrador se compara a uma criança ouvindo atentamente um fonógrafo, uma metáfora para a forma como ele absorve as experiências ao lado de uma pessoa que é descrita como um milagre. A chuva que desce pelo rosto dessa pessoa pode simbolizar tristeza ou um momento de revelação. A expressão 'holding your space' sugere um apoio silencioso durante um período difícil.

O coração partido é personificado como alguém que dirige um 'big black car', uma imagem que pode evocar a ideia de algo ameaçador e inevitável, talvez a dor ou o fim de um relacionamento. A música também aborda a dificuldade de expressar sentimentos ('Hope was a letter I never could send') e a sensação de impotência diante das adversidades ('Love was a country we couldn't defend'). A referência a um 'carnaval' onde se observa o movimento contínuo pode simbolizar a vida, com suas alegrias efêmeras e a inevitabilidade da mudança. Por fim, a música fecha com uma imagem de simplicidade e aceitação, onde o narrador se reconhece como uma 'plain jane', alguém comum, mas ainda assim desejoso de fazer parte das histórias e experiências da pessoa amada.	</sobre>
    </pirata>
    <pirata>
        <id>	4	</id>
        <nome>	Seiva	</nome>
        <recompensa>	Dia 23	</recompensa>
        <alcunha>		</alcunha>
        <sobre>	Não foi possível encontrar o significado então aqui está a letra:

        Naquela noite do dia 23
Passei o tempo todo olhando pra você
Tentando encontrar
Palavras pra dizer
Morena o seu gingado é sensacional
O seu sorriso mexe no sentimental
Já passei da fase
De me enganar
Teu brilho no meio da escuridão
Esclarece o impulso do meu coração
É nessa noite
Que eu conto pra você
Que já faz mais de mês
Que eu penso em nós dois
Na chance de te seduzir	</sobre>
    </pirata>
    <pirata>
        <id>	5	</id>
        <nome>	Bruno Major	</nome>
        <recompensa>	Regent's Park	</recompensa>
        <alcunha>		</alcunha>
        <sobre>	Regent's Park, uma faixa cativante do cantor e compositor britânico Bruno Major, mergulha nas emoções profundas associadas ao amor, à perda e à autodescoberta. Com sua voz emotiva e letras comoventes, Major leva o ouvinte a uma viagem introspectiva pelas profundezas da experiência humana. Esta composição sincera mostra o talento excepcional de Major na criação de música que ressoa com o público em um nível profundo.	</sobre>
    </pirata>
    <pirata>
        <id>	6	</id>
        <nome>	Laufey	</nome>
        <recompensa>	Falling Behind	</recompensa>
        <alcunha>		</alcunha>
        <sobre>	A Melancolia do Amor que Não Chega em 'Falling Behind'
A música 'Falling Behind', interpretada pela artista Laufey, é uma expressão lírica da sensação de descompasso com o mundo ao redor, especialmente no que diz respeito ao amor e aos relacionamentos. A letra reflete a experiência de se mudar para uma nova cidade e se sentir deslocado, observando a felicidade alheia e se perguntando por que o mesmo não acontece consigo.

A artista descreve um cenário onde o amor está no ar, mas ela se sente excluída dessa realidade. A metáfora do sol 'casado' com o céu e os amigos encontrando novos parceiros reforça a ideia de que todos ao seu redor estão avançando em suas vidas amorosas, enquanto ela permanece estagnada. A repetição da frase 'Everybody's falling in love and I'm falling behind' ressalta a sensação de estar ficando para trás.

Laufey utiliza elementos como a bossa nova para criar uma atmosfera de sonho e desejo por uma conexão amorosa. A música transmite uma melancolia suave, uma espécie de resignação diante da solidão, mas também uma esperança latente de que o amor eventualmente chegará. A vulnerabilidade expressa na canção é algo com que muitos ouvintes podem se identificar, tornando 'Falling Behind' uma obra tocante sobre a busca humana por amor e pertencimento.	</sobre>
    </pirata>
    <pirata>
        <id>	7	</id>
        <nome>	Eloise	</nome>
        <recompensa>	Left Side	</recompensa>
        <alcunha>		</alcunha>
        <sobre>	A canção "Left Side" de Eloïse é sobre a dificuldade de deixar ir uma relação passada. No primeiro verso, a cantora expressa a dificuldade de deixar, dizendo como é difícil esquecer o rosto do seu antigo amante e como devem dizer a si próprios uma mentira para fingir que o seu antigo amante nunca foi suficiente. O refrão fala então de como tentarão seguir em frente, tentando não olhar para ninguém que se pareça com o ex-amante, tentando ser suficientemente forte, mas no final não tendo a mesma pele dura que o ex-amante. No segundo verso, o cantor fala sobre como acabarão por sarar e um dia voltarão para o lado esquerdo da cama, que é onde experimentaram a dor da perda. A canção é, em última análise, sobre a força e coragem que é preciso ter para passar de uma relação passada e abraçar uma nova vida.	</sobre>
    </pirata>
    <pirata>
        <id>	8	</id>
        <nome>	Jack Johnson	</nome>
        <recompensa>	Banana Pancakes	</recompensa>
        <alcunha>		</alcunha>
        <sobre>	A Doçura dos Dias Chuvosos em 'Banana Pancakes' de Jack Johnson
A música 'Banana Pancakes', do cantor e compositor Jack Johnson, é uma ode aos pequenos prazeres da vida e à simplicidade de momentos compartilhados com alguém especial. A letra sugere uma manhã chuvosa, onde o clima serve como pretexto perfeito para ficar em casa, longe das obrigações do dia a dia. Johnson convida sua companheira a ignorar o mundo exterior e a desfrutar da companhia um do outro, propondo um dia de preguiça e intimidade. A referência a fazer 'panquecas de banana' e fingir que é fim de semana ressalta a ideia de criar um pequeno refúgio da rotina, onde o tempo parece parar.

Musicalmente, 'Banana Pancakes' é caracterizada pelo estilo suave e acústico de Jack Johnson, que combina elementos de folk e surf music. A canção transmite uma sensação de conforto e aconchego, que é amplificada pela voz calma e pelo som do ukulele, instrumento frequentemente associado à música havaiana e à descontração. A letra também brinca com a ideia de que a prática (de ficar na cama, de tocar ukulele) é agradável, pois é feita com a 'pequena dama' que o artista ama.

A mensagem central de 'Banana Pancakes' é a valorização do aqui e agora, e a importância de se desligar das preocupações cotidianas para apreciar momentos simples de felicidade. Johnson nos lembra que, às vezes, tudo o que precisamos está ao nosso alcance, dentro dos braços de quem amamos. A canção é um convite para acordar devagar, ignorar o telefone e o alarme, e simplesmente estar presente com quem se ama, especialmente em dias chuvosos onde o mundo lá fora pode	</sobre>
    </pirata>
    <pirata>
        <id>	9	</id>
        <nome>	Malcolm Todd	</nome>
        <recompensa>	Intercouse	</recompensa>
        <alcunha>		</alcunha>
        <sobre>	Intercourse speaks to the painful experience of a failed relationship and the lingering emotions that arise from it. The chorus sets the tone, as Malcolm Todd croons, “I wanna give you all my love, you left instead. Is the end of you in my bed?” These lines capture the raw vulnerability and longing that often accompany a breakup.

The verses of the song reveal a sense of longing and introspection. Todd reflects on the changes that occurred within the relationship, acknowledging that something has shifted. He sings, “Take time off, see if you can find it. Now we can’t get lost. I’m not mad at you, it’s just not the same feel.” These lyrics express a desire to recapture the lost connection and find solace in one another once again.	</sobre>
    </pirata>
    <pirata>
        <id>	10	</id>
        <nome>	Solomon Burke	</nome>
        <recompensa>	None Of Us Are Free	</recompensa>
        <alcunha>		</alcunha>
        <sobre>	A canção se concentra na ideia de que nenhum de nós pode realmente ser livre até que todos nós sejamos livres. Destaca a interconexão e a interdependência dos indivíduos, enfatizando que o nosso bem-estar está interligado com o bem-estar dos outros. Através de seus vocais cheios de alma, Burke toca em vários aspectos da condição humana, incluindo a desigualdade, a injustiça e as lutas enfrentadas por comunidades marginalizadas. As letras de Burke fornecem tanto uma reflexão sobre o estado do mundo quanto um chamado à ação. Ele canta sobre divisão, discriminação e a necessidade de unidade, lembrando aos ouvintes que a liberdade de um não deve vir à custa de outros. A canção carrega um senso de urgência, exortando os indivíduos a superar suas diferenças e trabalhar juntos em direção a uma sociedade mais equitativa e compassiva.	</sobre>
    </pirata>
        <pirata>
        <id>	11	</id>
        <nome>	Kendrick Lamar	</nome>
        <recompensa>	PRIDE.	</recompensa>
        <alcunha>		</alcunha>
        <sobre>	"PRIDE", de Kendrick Lamar, é uma canção poderosa que nos encoraja a examinar nossa relação com nós mesmos. Destaca a importância do amor próprio e nos lembra dos perigos do orgulho. Através de sua música, Kendrick Lamar está espalhando uma importante mensagem de autoaceitação e empoderamento. À medida que continuamos a lutar pelo sucesso e pela felicidade, devemos lembrar que a verdadeira alegria vem de dentro. Nas palavras de RuPaul, "Se você não pode amar a si mesmo, como diabos você vai amar outra pessoa?" Vamos levar a sério as palavras de Kendrick Lamar e praticar o amor a nós mesmos todos os dias.	</sobre>
    </pirata>
        <pirata>
        <id>	12	</id>
        <nome>	Douglas Germano	</nome>
        <recompensa>	Maria Da Vila Matilde	</recompensa>
        <alcunha>		</alcunha>
        <sobre> não foi possível encontrar significado da feita por Douglas Germano mas aqui a feita pela Elza Soares:
        
    A música 'Maria da Vila Matilde', interpretada pela icônica Elza Soares, é um poderoso hino de resistência contra a violência doméstica. A letra é um grito de empoderamento feminino, onde a protagonista, uma mulher que sofreu abusos, toma uma atitude decisiva para pôr fim ao ciclo de violência. Ela ameaça ligar para o número de denúncia de violência contra a mulher (180 no Brasil), demonstrando que não tem mais medo e que está pronta para enfrentar o agressor.

A canção utiliza uma linguagem direta e coloquial para expressar a revolta e a determinação da mulher em não mais tolerar a agressão. A repetição do verso 'Cê vai se arrepender de levantar a mão pra mim' funciona como um mantra de força e autoafirmação. A música também aborda a questão do machismo enraizado na sociedade, representado pela figura do homem que se acha no direito de agredir uma mulher, e a resposta da protagonista que subverte essa expectativa ao se defender e denunciar.

Elza Soares, conhecida por sua voz marcante e por abordar temas sociais em suas músicas, entrega em 'Maria da Vila Matilde' uma performance cheia de convicção e coragem. A canção se torna um símbolo de luta e conscientização, incentivando outras mulheres a não se calarem diante da violência e a buscarem ajuda. A música é um espelho da realidade de muitas mulheres e um chamado à ação para a sociedade.	</sobre>
    </pirata>
</recompensas>																														